migration_rollback/__init__.py
migration_rollback/apps.py
migration_rollback/management/__init__.py
migration_rollback/management/commands/__init__.py
migration_rollback/management/commands/migrateprevious.py
migration_rollback/management/commands/migraterollback.py
migration_rollback/utils/__init__.py
migration_rollback/utils/migration_utils.py
django_migration_rollback-1.0.5.dist-info/LICENSE
django_migration_rollback-1.0.5.dist-info/METADATA
django_migration_rollback-1.0.5.dist-info/WHEEL
django_migration_rollback-1.0.5.dist-info/top_level.txt
django_migration_rollback-1.0.5.dist-info/RECORD
