Metadata-Version: 2.1
Name: django-migration-rollback
Version: 1.0.5
Summary: A simple Django app to be able to migrate back to a previous migration or to migrate back to a migration in a specific branch in a git repository or locally.
Home-page: https://github.com/jdboisvert/django-migration-rollback
Author: Jeffrey Boisvert
Author-email: info.jeffreyboisvert@gmail.com
License: MIT License
Download-URL: https://github.com/jdboisvert/django-migration-rollback/archive/refs/tags/v1.0.5.zip
Project-URL: Repository, https://github.com/jdboisvert/django-migration-rollback
Project-URL: Bug Reports, https://github.com/jdboisvert/django-migration-rollback/issues
Keywords: django,migration,rollback,git
Platform: any
Classifier: Development Status :: 3 - Alpha
Classifier: Intended Audience :: Developers
Classifier: License :: OSI Approved :: MIT License
Classifier: Operating System :: OS Independent
Classifier: Programming Language :: Python :: 3.8
Classifier: Programming Language :: Python :: 3.9
Classifier: Programming Language :: Python :: 3.10
Classifier: Programming Language :: Python :: 3.11
Requires-Python: >=3.8.0
License-File: LICENSE
Requires-Dist: Django (>=3.1.14)
